selective_context/__init__.py
selective_context-0.1.4.dist-info/METADATA
selective_context-0.1.4.dist-info/WHEEL
selective_context-0.1.4.dist-info/top_level.txt
selective_context-0.1.4.dist-info/RECORD
