Metadata-Version: 2.1
Name: selective-context
Version: 0.1.4
Summary: Compress your prompt and context to let LLMs deal with 2x more content.
Author-email: Yucheng Li <liyucheng09@gmail.com>
Project-URL: repository, https://github.com/liyucheng09/Selective_Context
Keywords: nlp,llms,chatgpt
Classifier: License :: OSI Approved :: MIT License
Classifier: Programming Language :: Python
Classifier: Programming Language :: Python :: 3
Requires-Python: >=3.7
Requires-Dist: transformers
Requires-Dist: torch
Requires-Dist: nltk
Requires-Dist: spacy ==3.2.0
Requires-Dist: numpy
Requires-Dist: click ==8.0.4
